odoo/addons/fieldservice_vehicle_stock/README.rst
odoo/addons/fieldservice_vehicle_stock/__init__.py
odoo/addons/fieldservice_vehicle_stock/__manifest__.py
odoo/addons/fieldservice_vehicle_stock/data/fsm_stock_data.xml
odoo/addons/fieldservice_vehicle_stock/i18n/de.po
odoo/addons/fieldservice_vehicle_stock/i18n/es.po
odoo/addons/fieldservice_vehicle_stock/i18n/es_AR.po
odoo/addons/fieldservice_vehicle_stock/i18n/es_CL.po
odoo/addons/fieldservice_vehicle_stock/i18n/fieldservice_vehicle_stock.pot
odoo/addons/fieldservice_vehicle_stock/i18n/it.po
odoo/addons/fieldservice_vehicle_stock/i18n/pt_BR.po
odoo/addons/fieldservice_vehicle_stock/i18n/pt_PT.po
odoo/addons/fieldservice_vehicle_stock/models/__init__.py
odoo/addons/fieldservice_vehicle_stock/models/fsm_order.py
odoo/addons/fieldservice_vehicle_stock/models/fsm_vehicle.py
odoo/addons/fieldservice_vehicle_stock/models/product_putaway.py
odoo/addons/fieldservice_vehicle_stock/models/stock_picking.py
odoo/addons/fieldservice_vehicle_stock/readme/CONFIGURE.rst
odoo/addons/fieldservice_vehicle_stock/readme/CONTRIBUTORS.rst
odoo/addons/fieldservice_vehicle_stock/readme/CREDITS.rst
odoo/addons/fieldservice_vehicle_stock/readme/DESCRIPTION.rst
odoo/addons/fieldservice_vehicle_stock/readme/ROADMAP.rst
odoo/addons/fieldservice_vehicle_stock/security/ir.model.access.csv
odoo/addons/fieldservice_vehicle_stock/static/description/icon.png
odoo/addons/fieldservice_vehicle_stock/static/description/index.html
odoo/addons/fieldservice_vehicle_stock/tests/__init__.py
odoo/addons/fieldservice_vehicle_stock/tests/test_fsm_order.py
odoo/addons/fieldservice_vehicle_stock/tests/test_product_putaway.py
odoo/addons/fieldservice_vehicle_stock/tests/test_stock_picking.py
odoo/addons/fieldservice_vehicle_stock/views/fsm_vehicle.xml
odoo/addons/fieldservice_vehicle_stock/views/stock_picking.xml
odoo14_addon_fieldservice_vehicle_stock-14.0.1.1.1.dist-info/METADATA
odoo14_addon_fieldservice_vehicle_stock-14.0.1.1.1.dist-info/WHEEL
odoo14_addon_fieldservice_vehicle_stock-14.0.1.1.1.dist-info/top_level.txt
odoo14_addon_fieldservice_vehicle_stock-14.0.1.1.1.dist-info/RECORD
