Metadata-Version: 2.1
Name: odoo14-addon-fieldservice-vehicle-stock
Version: 14.0.1.1.1
Summary: Track inventory of Field Service vehicles
Home-page: https://github.com/OCA/field-service
Author: Open Source Integrators, Brian McMaster, Odoo Community Association (OCA)
Author-email: support@odoo-community.org
License: AGPL-3
Platform: UNKNOWN
Classifier: Programming Language :: Python
Classifier: Framework :: Odoo
Classifier: Framework :: Odoo :: 14.0
Classifier: License :: OSI Approved :: GNU Affero General Public License v3
Classifier: Development Status :: 4 - Beta
Requires-Python: >=3.6
Requires-Dist: odoo14-addon-fieldservice-stock
Requires-Dist: odoo14-addon-fieldservice-vehicle
Requires-Dist: odoo14-addon-stock-putaway-method
Requires-Dist: odoo <14.1dev,>=14.0a
